mmap_ninja/__init__.py
mmap_ninja/base.py
mmap_ninja/generic.py
mmap_ninja/numpy.py
mmap_ninja/ragged.py
mmap_ninja/sorter.py
mmap_ninja/string.py
mmap_ninja-0.8.0.dist-info/licenses/LICENSE
mmap_ninja-0.8.0.dist-info/METADATA
mmap_ninja-0.8.0.dist-info/WHEEL
mmap_ninja-0.8.0.dist-info/top_level.txt
mmap_ninja-0.8.0.dist-info/RECORD
